Workbook

Sheet Read me
B2: Agent cost and capacity calculator
B3: Modelling what context drift does to cost and to capacity
B6: The question this answers
C7: Input size grows as people learn what a system can do — longer questions, richer history, more tool results in context. Traffic can be flat while the bill and the capacity envelope both move. These scenarios model that, holding volume constant and changing only the size of a turn.
B9: The three scenarios
B10: Today | C10: Your measured average input size. The starting point.
B11: p95 as the norm | C11: Every call now carries today's 95th-percentile input size. This is the realistic end state of drift, not a worst case.
B13: Two sheets of assumptions, on purpose
B14: Inputs | C14: Client context — volumes, turn structure, token sizes, model mix, tier baseline, PT commitment. Calibrated per engagement, edited often.
B15: Platform rates | C15: Vendor prices and throughput constants — model prices, burndown weights, GSU throughput, PT prices by term. Changed only when Google changes them.
B17: Cell conventions
B18: Yellow fill, blue text | C18: A client input, on the Inputs sheet. Edit these often.
B19: Purple fill, purple text | C19: A platform rate. Edit these when prices change.
B20: Black text | C20: A formula. Leave alone.
B21: Green text | C21: A direct reference to another sheet.
B22: Cream fill | C22: A headline result worth quoting.
B24: Reading order
B25: 1. | C25: Inputs — set today's average and p95 input tokens from your own traces. These two numbers drive everything else.
B26: 2. | C26: Demand — watch three rows in particular: the cached share of the input, the turn duration, and the peak TPM against your tier baseline. All three move on drift alone, with no change in traffic.
B27: 3. | C27: Cost — cost per conversation, the monthly bill, and the increase versus today. The effective price per million input tokens is the row that explains why cost outruns token count.
B28: 4. | C28: PT sizing — how many GSUs the same traffic needs in each scenario, and the break-even utilisation that decides the term.
B29: 5. | C29: Total cost — the all-in monthly figure: commitment plus spill-over plus the models that never run on PT, against pure pay-as-you-go.
B31: The mechanism worth understanding
B32: Cache dilution | C32: The cacheable prefix — instructions, policy text, tool schemas — is fixed in size. History and tool results are what grow. So as input rises, the cached share falls and the blended price per input token climbs toward the full rate. Cost grows faster than the token count does.
B33: Longer turns | C33: A larger context takes longer to prefill, so turns lengthen. By Little's law that means more turns in flight at the same arrival rate, and each turn burns tokens faster — so the number of turns your tier baseline can admit falls. Drift shrinks the admission cap without anyone changing a setting.
B35: What this model does not include
C36: Compute, storage, queue and networking costs — small next to the model bill, but not zero.
C37: Retrieval and embedding costs, evaluation runs, and tokens spent on turns that are retried or shed.
C38: Output growth. Longer inputs often produce longer answers; output tokens are held constant here, so raise them by hand if your traces disagree.
C39: Downstream system load and the human-cost comparison — deliberately out of scope, tracked separately.

Sheet Platform rates
B1: Platform rates — vendor prices and throughput constants
B2: Verified September 2026, global endpoint, list prices. These change on Google's schedule — re-confirm before any commitment, then edit here only.
B4: MODEL PRICES — $ PER 1 MILLION TOKENS
B5: Model | C5: Input | D5: Cached input | E5: Output | F5: Note
B6: Standard model — Gemini 3.5 Flash | C6: 1.5 | D6: 0.15 | E6: 9 | F6: Introductory pricing on 3.6–3.8 Flash ends 31 December 2026
B7: Lite model — 3.5 Flash-Lite | C7: 0.3 | D7: 0.03 | E7: 2.5
B8: Pro model — 3.1 Pro Preview | C8: 2 | D8: 0.2 | E8: 12 | F8: Doubles above 200k context
B9: Regional endpoints add 10%. Priority tier 1.8×; Flex and Batch 0.5×. Cached input is billed at 10% of the input rate.
B11: THROUGHPUT AND BURNDOWN
B12: GSU throughput | C12: 675 | D12: burndown tokens/s | E12: One generative-scale unit of the standard model
B13: Burndown weight — uncached input | C13: 1 | D13: ×
B14: Burndown weight — cached input | C14: 0.1 | D14: ×
B15: Burndown weight — output | C15: 6 | D15: × | E15: Output dominates PT sizing
B16: Pay-as-you-go price per 1M burndown tokens | C16: 1.5 | D16: $ | E16: Equals the standard model's input price — the weights mirror the price ratios
B17: Added turn seconds per 1,000 extra input tokens | C17: 0.1 | D17: seconds | E17: Prefill cost of a larger context. Measure and replace this
B18: Minimum cacheable prefix | C18: 4096 | D18: tokens | E18: 6,144 on 3.7/3.8 Flash and 3.1 Pro. Below this, no caching at all
B19: Check — spill-over pricing identity | C19: =IF(AND(ABS($D$6-$C$6*C14)<0.0001,ABS($E$6-$C$6*C15)<0.0001,ABS(C16-$C$6)<0.0001),"OK — exact","APPROXIMATE — prices no longer mirror the burndown weights") -> OK — exact | E19: Spill-over cost is burndown tokens × the standard model's input price. That is exact only while cached and output prices are the same multiples of the input price as their burndown weights.
B21: PROVISIONED THROUGHPUT — $ PER GSU-HOUR BY TERM
B22: 1 week term | C22: 7.14 | D22: $
B23: 1 month term | C23: 3.7 | D23: $
B24: 3 month term | C24: 3.29 | D24: $
B25: 1 year term | C25: 2.74 | D25: $ | E25: Usually the only term that can beat pay-as-you-go

Sheet Demand
B1: Turn shape, token demand and concurrency by scenario
B2: Volume is held constant in both columns. Only the size of a turn changes — which is what drift does to a live system.
B4: VOLUME AND RATES — CONSTANT ACROSS SCENARIOS
B5: Conversations per second, daily average | C5: =Inputs!$C$5/86400 -> 0.76388889
B6: Turns per second, daily average | C6: =C5*Inputs!$C$6 -> 0.91666667
B7: Turns per second, peak hour | C7: =C6*Inputs!$C$11 -> 2.75
B8: Model calls per second, daily average | C8: =C6*Inputs!$C$7 -> 3.025
B9: Model calls per second, peak hour | C9: =C8*Inputs!$C$11 -> 9.075
B10: Conversations in the daily peak block | C10: =Inputs!$C$5/24*Inputs!$C$11*Inputs!$C$12 -> 24750 | G10: Peak and off-peak blocks sum to the daily volume
B11: Conversations in the off-peak block | C11: =Inputs!$C$5-C10 -> 41250
B12: Model calls per second, off-peak | C12: =C11/(24-Inputs!$C$12)*Inputs!$C$6*Inputs!$C$7/3600 -> 2.1607143
B13: Tool calls per second, peak hour | C13: =C7*Inputs!$C$8 -> 8.25 | G13: Unaffected by token size
B14: Check — peak hours × multiplier must stay under 24 | C14: =IF(Inputs!$C$12*Inputs!$C$11<24,"OK","FIX — the peak block exceeds the day's volume") -> OK
B16: TURN SHAPE BY SCENARIO
C17: Today — measured average | D17: p95 as the norm | G17: Note
B18: Input tokens per model call | C18: =Inputs!$C$15 -> 15836 | D18: =Inputs!$C$16 -> 68809 | G18: The drift axis
B19: Stable cacheable prefix | C19: =Inputs!$C$17 -> 9266 | D19: =Inputs!$C$17 -> 9266 | G19: Fixed in absolute terms — only history and tool results grow
B20: Effective cache hit rate | C20: =IF(C19>='Platform rates'!$C$18,Inputs!$C$18,0) -> 0.672 | D20: =IF(D19>='Platform rates'!$C$18,Inputs!$C$18,0) -> 0.672 | G20: Forced to zero if the prefix is below the platform's cache minimum
B21: Cached input tokens per call | C21: =MIN(C19,C18)*C20 -> 6226.752 | D21: =MIN(D19,D18)*D20 -> 6226.752 | G21: Billed at 10% of the input price
B22: Uncached input tokens per call | C22: =C18-C21 -> 9609.248 | D22: =D18-D21 -> 62582.248 | G22: Billed at the full rate
B23: Cached share of the input | C23: =C21/C18 -> 0.39320232 | D23: =D21/D18 -> 0.090493278 | G23: This is what erodes as the input grows — the cost driver behind drift
B24: Output tokens per call | C24: =Inputs!$C$19 -> 529 | D24: =Inputs!$C$19 -> 529 | G24: Held constant; raise it if longer inputs also produce longer answers
B25: Turn duration, p50 | C25: =Inputs!$C$9+Inputs!$C$7*(C18-Inputs!$C$15)/1000*'Platform rates'!$C$17 -> 6 | D25: =Inputs!$C$9+Inputs!$C$7*(D18-Inputs!$C$15)/1000*'Platform rates'!$C$17 -> 23.48109 | G25: Larger contexts take longer to prefill
B26: Prefix clears the cache minimum? | C26: =IF(C19>='Platform rates'!$C$18,"Yes","No — no caching at all") -> Yes | D26: =IF(D19>='Platform rates'!$C$18,"Yes","No — no caching at all") -> Yes
B28: TOKEN DEMAND BY SCENARIO
B29: Input tokens per minute, daily average | C29: =$C$8*C18*60 -> 2874234 | D29: =$C$8*D18*60 -> 12488833
B30: Input tokens per minute, peak hour | C30: =$C$9*C18*60 -> 8622702 | D30: =$C$9*D18*60 -> 37466500
B31: Output tokens per minute, peak hour | C31: =$C$9*C24*60 -> 288040.5 | D31: =$C$9*D24*60 -> 288040.5
B32: Average TPM vs the organisation baseline | C32: =C29/Inputs!$C$29 -> 0.2874234 | D32: =D29/Inputs!$C$29 -> 1.2488833
B33: Peak TPM vs the organisation baseline | C33: =C30/Inputs!$C$29 -> 0.8622702 | D33: =D30/Inputs!$C$29 -> 3.74665 | G33: Above 1.00× at peak means shaping or buying capacity
B34: Verdict at the peak hour | C34: =IF(C33<=0.8,"Comfortable",IF(C33<=1,"Close to the baseline","Above the baseline — shape demand or buy capacity")) -> Close to the baseline | D34: =IF(D33<=0.8,"Comfortable",IF(D33<=1,"Close to the baseline","Above the baseline — shape demand or buy capacity")) -> Above the baseline — shape demand or buy capacity | G34: Note this can go red on drift alone, with no traffic growth at all
B36: CONCURRENCY AND THE ADMISSION CAP
B37: In-flight turns at the peak hour | C37: =$C$7*C25 -> 16.5 | D37: =$C$7*D25 -> 64.572997 | G37: Sizes orchestrator memory, session locks and model concurrency
B38: Concurrent sessions at the peak hour | C38: =$C$7*(C25+Inputs!$C$10) -> 181.5 | D38: =$C$7*(D25+Inputs!$C$10) -> 229.573 | G38: Sizes open streaming connections and hot session state
B39: Tokens consumed per turn | C39: =Inputs!$C$7*(C18+C24) -> 54004.5 | D39: =Inputs!$C$7*(D18+D24) -> 228815.4
B40: Tokens per second per in-flight turn | C40: =C39/C25 -> 9000.75 | D40: =D39/D25 -> 9744.6669
B41: In-flight turns the baseline sustains | C41: =Inputs!$C$29/60/C40 -> 18.516975 | D41: =Inputs!$C$29/60/D40 -> 17.103372 | G41: The starting value for the admission controller's in-flight cap
B42: Turns per second the baseline sustains | C42: =C41/C25 -> 3.0861626 | D42: =D41/D25 -> 0.7283892
B43: Headroom at the peak hour (turns per second) | C43: =C42-$C$7 -> 0.33616257 | D43: =D42-$C$7 -> -2.0216108 | G43: Negative means demand exceeds what the token budget admits
B44: Share of peak demand that must be shed | C44: =MAX(0,1-C42/$C$7) -> 0 | D44: =MAX(0,1-D42/$C$7) -> 0.7351312 | G44: Drift shrinks the cap while demand stays the same

Sheet Cost
B1: Cost by scenario — what context drift does to the bill
B2: Same traffic in every column. The only thing that changes is the size of a turn.
B4: COST PER MODEL CALL
C5: Today — measured average | D5: p95 as the norm | G5: Note
B6: Standard model | C6: =(Demand!C22*'Platform rates'!$C$6+Demand!C21*'Platform rates'!$D$6+Demand!C24*'Platform rates'!$E$6)/1000000 -> 0.020108885 | D6: =(Demand!D22*'Platform rates'!$C$6+Demand!D21*'Platform rates'!$D$6+Demand!D24*'Platform rates'!$E$6)/1000000 -> 0.099568385
B7: Lite model | C7: =(Demand!C22*'Platform rates'!$C$7+Demand!C21*'Platform rates'!$D$7+Demand!C24*'Platform rates'!$E$7)/1000000 -> 0.004392077 | D7: =(Demand!D22*'Platform rates'!$C$7+Demand!D21*'Platform rates'!$D$7+Demand!D24*'Platform rates'!$E$7)/1000000 -> 0.020283977
B8: Pro model | C8: =(Demand!C22*'Platform rates'!$C$8+Demand!C21*'Platform rates'!$D$8+Demand!C24*'Platform rates'!$E$8)/1000000 -> 0.026811846 | D8: =(Demand!D22*'Platform rates'!$C$8+Demand!D21*'Platform rates'!$D$8+Demand!D24*'Platform rates'!$E$8)/1000000 -> 0.13275785
B9: Blended cost per model call | C9: =C6*Inputs!$C$23+C7*Inputs!$C$24+C8*Inputs!$C$25 -> 0.020108885 | D9: =D6*Inputs!$C$23+D7*Inputs!$C$24+D8*Inputs!$C$25 -> 0.099568385 | G9: Weighted by the model mix
B10: Effective price per 1M input tokens | C10: =(Demand!C22*'Platform rates'!$C$6+Demand!C21*'Platform rates'!$D$6)/Demand!C18 -> 0.96917686 | D10: =(Demand!D22*'Platform rates'!$C$6+Demand!D21*'Platform rates'!$D$6)/Demand!D18 -> 1.3778341 | G10: Rises as the cached share erodes, even though list prices never move
B12: COST PER TURN, CONVERSATION AND MONTH
B13: Cost per turn | C13: =C9*Inputs!$C$7 -> 0.06635932 | D13: =D9*Inputs!$C$7 -> 0.32857567
B14: Cost per conversation | C14: =C13*Inputs!$C$6 -> 0.079631184 | D14: =D13*Inputs!$C$6 -> 0.3942908 | G14: The number to compare with a human-handled contact
B15: Conversations per month | C15: =Inputs!$C$5*Inputs!$C$35 -> 1320000 | D15: =Inputs!$C$5*Inputs!$C$35 -> 1320000
B16: Model cost per month | C16: =C14*C15 -> 105113.16 | D16: =D14*D15 -> 520463.86 | G16: Pure pay-as-you-go, no commitment
B17: Increase vs today | C17: =C16/$C$16-1 -> 0 | D17: =D16/$C$16-1 -> 3.9514623 | G17: The cost of drift, with no extra users and no price change
B18: Extra dollars per month vs today | C18: =C16-$C$16 -> 0 | D18: =D16-$C$16 -> 415350.7
B20: WHAT THE LEVERS ARE WORTH — AT THE p95-AS-NORM SCENARIO
B21: Configuration | C21: $ per conversation | D21: $ per month | E21: vs no caching | G21: Note
B22: No caching, all calls on the standard model | C22: =(Demand!$D$18*'Platform rates'!$C$6+Demand!$D$24*'Platform rates'!$E$6)/1000000*Inputs!$C$6*Inputs!$C$7 -> 0.42757902 | D22: =C22*$D$15 -> 564404.31 | E22: =C22/$C$22-1 -> 0 | G22: Prefix not stable, or below the cache minimum
B23: Prefix cached, all calls on the standard model | C23: =$D$6*Inputs!$C$6*Inputs!$C$7 -> 0.3942908 | D23: =C23*$D$15 -> 520463.86 | E23: =C23/$C$22-1 -> -0.077852782 | G23: Caching alone, no routing
B24: Prefix cached plus the model mix on Inputs | C24: =$D$14 -> 0.3942908 | D24: =C24*$D$15 -> 520463.86 | E24: =C24/$C$22-1 -> -0.077852782 | G24: Routing and caching together — the current design

Sheet Inputs
B1: Client context — the assumptions to calibrate
B2: Edit the yellow cells. Vendor prices and throughput constants live on the Platform rates sheet, because they change on Google's schedule, not yours.
B4: VOLUME AND TURN STRUCTURE
B5: Conversations per day | C5: 66000 | D5: conversations | E5: Total across all channels, at today's volume
B6: Turns per conversation | C6: 1.2 | D6: turns | E6: One turn = one user message and the agent's full response
B7: Model calls per turn | C7: 3.3 | D7: calls | E7: Plan, answer, and sometimes a third call
B8: Tool calls per turn | C8: 3 | D8: calls | E8: Average across intents
B9: Turn duration today, p50 | C9: 6 | D9: seconds | E9: At today's input size. Larger inputs lengthen this automatically
B10: User think time between turns | C10: 60 | D10: seconds | E10: Drives concurrent sessions, not in-flight turns
B11: Peak-hour multiplier vs daily average | C11: 3 | D11: × | E11: Busiest hour divided by the 24-hour average
B12: Hours per day at the peak rate | C12: 3 | D12: hours | E12: Shapes the daily profile used for spill-over
B14: INPUT TOKEN SIZE — THE DRIFT AXIS
B15: Input tokens per model call — today's average | C15: 15836 | D15: tokens | E15: Measured from traces
B16: Input tokens per model call — p95 | C16: 68809 | D16: tokens | E16: The tail you are already serving, observed in QA
B17: Stable cacheable prefix, today | C17: 9266 | D17: tokens | E17: Must clear the cache minimum on Platform rates or nothing caches at all
B18: Prefix cache hit rate | C18: 0.672 | D18: % | E18: Share of calls where the prefix is served from cache
B19: Output tokens per model call | C19: 529 | D19: tokens | E19: Including thinking tokens, which are billed as output
B20: Only the variable part of the input grows — history, user text and tool results. The prefix stays fixed in absolute terms, so its share of the input shrinks as the input grows. That is why cost rises faster than token count.
B22: MODEL MIX — SHARE OF MODEL CALLS
B23: Standard model | C23: 1 | D23: %
B24: Lite model | C24: 0 | D24: % | E24: Routing, classification, short answers
B25: Pro model | C25: 0 | D25: % | E25: Rare hard cases only
B26: Check — must total 100% | C26: =SUM(C23:C25) -> 1 | E26: =IF(ABS(C26-1)<0.0001,"OK","FIX — shares must total 100%") -> OK
B28: CAPACITY AND COMMITMENT
B29: Organisation TPM baseline for this model family | C29: 10000000 | D29: tokens/min | E29: Set by rolling 30-day spend across the whole organisation
B30: Share of model calls carried on Provisioned Throughput | C30: 1 | D30: % | E30: Typically the standard-model share; the rest is always pay-as-you-go
B31: GSUs to actually purchase | C31: 212 | D31: GSUs | E31: The lever. See the Total cost sheet for what each choice costs all-in
B32: Spill-over tier price multiplier | C32: 1 | D32: × | E32: 1.0 Standard · 1.8 Priority · 0.5 Flex
B34: OPERATING
B35: Days per month | C35: 20 | D35: days

Sheet PT sizing
B1: Provisioned Throughput sizing and break-even
B2: PT buys an SLA and freedom from contention on the shared pool. It is only cheaper than pay-as-you-go on a long term at high utilisation.
B4: BURNDOWN AND SIZING BY SCENARIO
C5: Today — measured average | D5: p95 as the norm | G5: Note
B6: Burndown tokens per model call | C6: =Demand!C22*'Platform rates'!$C$13+Demand!C21*'Platform rates'!$C$14+Demand!C24*'Platform rates'!$C$15 -> 13405.923 | D6: =Demand!D22*'Platform rates'!$C$13+Demand!D21*'Platform rates'!$C$14+Demand!D24*'Platform rates'!$C$15 -> 66378.923 | G6: Output is weighted 6×, which is why it dominates
B7: Model calls per second per GSU | C7: ='Platform rates'!$C$12/C6 -> 0.050350878 | D7: ='Platform rates'!$C$12/D6 -> 0.01016889
B8: GSUs for all standard-model calls, daily average | C8: =ROUNDUP(Demand!$C$8*Inputs!$C$23/C7,0) -> 61 | D8: =ROUNDUP(Demand!$C$8*Inputs!$C$23/D7,0) -> 298 | G8: Sizing guidance, shown whatever the PT share is set to
B9: GSUs for all standard-model calls, peak hour | C9: =ROUNDUP(Demand!$C$9*Inputs!$C$23/C7,0) -> 181 | D9: =ROUNDUP(Demand!$C$9*Inputs!$C$23/D7,0) -> 893 | G9: Sizing here leaves the units idle most of the day
B11: BREAK-EVEN UTILISATION BY TERM — INDEPENDENT OF SCENARIO
B12: Term | C12: $ per GSU-hour | D12: $ per 1M burndown tokens at 100% use | E12: Break-even utilisation vs PayGo | G12: Note
B13: 1 week | C13: ='Platform rates'!$C$22 -> 7.14 | D13: =C13/('Platform rates'!$C$12*3600/1000000) -> 2.9382716 | E13: =D13/'Platform rates'!$C$16 -> 1.9588477 | G13: =IF(E13>1,"Never cheaper than pay-as-you-go","Cheaper above "&TEXT(E13,"0%")&" utilisation") -> Never cheaper than pay-as-you-go
B14: 1 month | C14: ='Platform rates'!$C$23 -> 3.7 | D14: =C14/('Platform rates'!$C$12*3600/1000000) -> 1.5226337 | E14: =D14/'Platform rates'!$C$16 -> 1.0150892 | G14: =IF(E14>1,"Never cheaper than pay-as-you-go","Cheaper above "&TEXT(E14,"0%")&" utilisation") -> Never cheaper than pay-as-you-go
B15: 3 months | C15: ='Platform rates'!$C$24 -> 3.29 | D15: =C15/('Platform rates'!$C$12*3600/1000000) -> 1.3539095 | E15: =D15/'Platform rates'!$C$16 -> 0.90260631 | G15: =IF(E15>1,"Never cheaper than pay-as-you-go","Cheaper above "&TEXT(E15,"0%")&" utilisation") -> Cheaper above 90% utilisation
B16: 1 year | C16: ='Platform rates'!$C$25 -> 2.74 | D16: =C16/('Platform rates'!$C$12*3600/1000000) -> 1.127572 | E16: =D16/'Platform rates'!$C$16 -> 0.75171468 | G16: =IF(E16>1,"Never cheaper than pay-as-you-go","Cheaper above "&TEXT(E16,"0%")&" utilisation") -> Cheaper above 75% utilisation

Sheet Total cost
B1: Total monthly cost — Provisioned Throughput plus pay-as-you-go spill-over
B2: PT is a fixed monthly commitment whether you use it or not. Demand above its capacity spills over to pay-as-you-go. This sheet adds the two together, for each drift scenario.
B4: THE PURCHASE
B5: GSUs to purchase | C5: =Inputs!$C$31 -> 212 | H5: Edit on the Inputs sheet
B6: Spill-over tier price multiplier | C6: =Inputs!$C$32 -> 1 | H6: 1.0 Standard · 1.8 Priority · 0.5 Flex
B7: PT capacity purchased | C7: =C5*'Platform rates'!$C$12 -> 143100 | H7: Burndown tokens per second, available around the clock
B8: Model calls per month | C8: =Inputs!$C$5*Inputs!$C$35*Inputs!$C$6*Inputs!$C$7 -> 5227200
B9: Check — the GSU lever needs a PT share above zero | C9: =IF(AND(C5>0,Inputs!$C$30=0),"FIX — GSUs purchased but 0% of calls routed to PT: pure added cost",IF(AND(C5=0,Inputs!$C$30>0),"FIX — calls routed to PT but 0 GSUs purchased",IF(C5=0,"No commitment — everything is pay-as-you-go","OK"))) -> OK
B11: SPILL-OVER BY SCENARIO
C12: Today — measured average | D12: p95 as the norm | H12: Note
B13: Burndown tokens/s on PT, peak block | C13: =Demand!$C$9*Inputs!$C$30*'PT sizing'!C6 -> 121658.75 | D13: =Demand!$C$9*Inputs!$C$30*'PT sizing'!D6 -> 602388.73
B14: Burndown tokens/s on PT, off-peak block | C14: =Demand!$C$12*Inputs!$C$30*'PT sizing'!C6 -> 28966.37 | D14: =Demand!$C$12*Inputs!$C$30*'PT sizing'!D6 -> 143425.89
B15: Burndown served by PT, per month | C15: =MIN(C13,$C$7)*3600*Inputs!$C$12*Inputs!$C$35+MIN(C14,$C$7)*3600*(24-Inputs!$C$12)*Inputs!$C$35 -> 7.0075442e+10 | D15: =MIN(D13,$C$7)*3600*Inputs!$C$12*Inputs!$C$35+MIN(D14,$C$7)*3600*(24-Inputs!$C$12)*Inputs!$C$35 -> 247276800000
B16: Burndown spilled to pay-as-you-go, per month | C16: =MAX(0,C13-$C$7)*3600*Inputs!$C$12*Inputs!$C$35+MAX(0,C14-$C$7)*3600*(24-Inputs!$C$12)*Inputs!$C$35 -> 0 | D16: =MAX(0,D13-$C$7)*3600*Inputs!$C$12*Inputs!$C$35+MAX(0,D14-$C$7)*3600*(24-Inputs!$C$12)*Inputs!$C$35 -> 9.9699107e+10 | H16: Priced at the spill-over tier
B17: PT utilisation averaged over the month | C17: =IF($C$7=0,0,C15/($C$7*3600*24*Inputs!$C$35)) -> 0.28338866 | D17: =IF($C$7=0,0,D15/($C$7*3600*24*Inputs!$C$35)) -> 1 | H17: Compare with the break-even utilisation on the PT sizing sheet
B19: THE GSU LEVER — HOW FAR IT CAN GO
C20: Today — measured average | D20: p95 as the norm | H20: Note
B21: GSUs you can keep saturated around the clock | C21: =ROUNDDOWN(Demand!$C$12*Inputs!$C$23*'PT sizing'!C6/'Platform rates'!$C$12,0) -> 42 | D21: =ROUNDDOWN(Demand!$C$12*Inputs!$C$23*'PT sizing'!D6/'Platform rates'!$C$12,0) -> 212 | H21: Capacity must sit below the off-peak trough to stay fully used. Shown whatever the PT share is set to
B22: Saving per saturated GSU, 1-year term | C22: ='Platform rates'!$C$12*3600*24*Inputs!$C$35/1000000*'Platform rates'!$C$16-'Platform rates'!$C$25*24*Inputs!$C$35 -> 434.4 | D22: ='Platform rates'!$C$12*3600*24*Inputs!$C$35/1000000*'Platform rates'!$C$16-'Platform rates'!$C$25*24*Inputs!$C$35 -> 434.4 | H22: Fixed per GSU while it stays saturated — the same in both columns
B23: Best case saving from the GSU lever | C23: =C21*C22 -> 18244.8 | D23: =D21*D22 -> 92092.8 | H23: Buy what you can keep busy; a GSU sized for the peak sits idle and loses money
B25: TOTAL MONTHLY COST BY TERM — THE ANSWER
C26: Today — measured average | D26: p95 as the norm | H26: Note
B27: PT on a 1 week term | C27: =$C$5*'Platform rates'!$C$22*24*Inputs!$C$35+C16/1000000*'Platform rates'!$C$16*$C$6+(Cost!C9-Cost!C6*Inputs!$C$30)*$C$8 -> 726566.4 | D27: =$C$5*'Platform rates'!$C$22*24*Inputs!$C$35+D16/1000000*'Platform rates'!$C$16*$C$6+(Cost!D9-Cost!D6*Inputs!$C$30)*$C$8 -> 876115.06
B28: PT on a 1 month term | C28: =$C$5*'Platform rates'!$C$23*24*Inputs!$C$35+C16/1000000*'Platform rates'!$C$16*$C$6+(Cost!C9-Cost!C6*Inputs!$C$30)*$C$8 -> 376512 | D28: =$C$5*'Platform rates'!$C$23*24*Inputs!$C$35+D16/1000000*'Platform rates'!$C$16*$C$6+(Cost!D9-Cost!D6*Inputs!$C$30)*$C$8 -> 526060.66
B29: PT on a 3 month term | C29: =$C$5*'Platform rates'!$C$24*24*Inputs!$C$35+C16/1000000*'Platform rates'!$C$16*$C$6+(Cost!C9-Cost!C6*Inputs!$C$30)*$C$8 -> 334790.4 | D29: =$C$5*'Platform rates'!$C$24*24*Inputs!$C$35+D16/1000000*'Platform rates'!$C$16*$C$6+(Cost!D9-Cost!D6*Inputs!$C$30)*$C$8 -> 484339.06
B30: PT on a 1 year term | C30: =$C$5*'Platform rates'!$C$25*24*Inputs!$C$35+C16/1000000*'Platform rates'!$C$16*$C$6+(Cost!C9-Cost!C6*Inputs!$C$30)*$C$8 -> 278822.4 | D30: =$C$5*'Platform rates'!$C$25*24*Inputs!$C$35+D16/1000000*'Platform rates'!$C$16*$C$6+(Cost!D9-Cost!D6*Inputs!$C$30)*$C$8 -> 428371.06 | H30: Commitment + spill-over + models never on PT
B31: Pure pay-as-you-go, no commitment | C31: =Cost!C16 -> 105113.16 | D31: =Cost!D16 -> 520463.86 | H31: The baseline every row above is measured against
B32: Best PT term vs pure pay-as-you-go | C32: =MIN(C27,C28,C29,C30)-C31 -> 173709.24 | D32: =MIN(D27,D28,D29,D30)-D31 -> -92092.8 | H32: Positive means PT costs more — you are buying the SLA, not a discount
B33: Cheapest option | C33: =IF(C32<0,"Provisioned Throughput","Pure pay-as-you-go") -> Pure pay-as-you-go | D33: =IF(D32<0,"Provisioned Throughput","Pure pay-as-you-go") -> Provisioned Throughput
B35: COMPONENT BREAKDOWN ON THE 1-YEAR TERM
C36: Today — measured average | D36: p95 as the norm | H36: Note
B37: PT commitment | C37: =$C$5*'Platform rates'!$C$25*24*Inputs!$C$35 -> 278822.4 | D37: =$C$5*'Platform rates'!$C$25*24*Inputs!$C$35 -> 278822.4 | H37: Fixed, whether you use the capacity or not
B38: Spill-over on the standard model | C38: =C16/1000000*'Platform rates'!$C$16*$C$6 -> 0 | D38: =D16/1000000*'Platform rates'!$C$16*$C$6 -> 149548.66
B39: Models never carried on PT | C39: =(Cost!C9-Cost!C6*Inputs!$C$30)*$C$8 -> 0 | D39: =(Cost!D9-Cost!D6*Inputs!$C$30)*$C$8 -> 0 | H39: Lite and Pro calls are always pay-as-you-go
B40: Total per month | C40: =C37+C38+C39 -> 278822.4 | D40: =D37+D38+D39 -> 428371.06
B41: Effective cost per conversation | C41: =C40/Cost!C15 -> 0.21122909 | D41: =D40/Cost!D15 -> 0.32452353
B43: Two things to notice as you move right across these columns. The GSUs needed to serve the same traffic rise with the input size, so a commitment sized for today is progressively outgrown — check the PT sizing sheet. And the spill-over line grows faster than the commitment line, because everything above the fixed capacity is billed at full pay-as-you-go rates.
